Lab6/Ejercicio5/flipflop.v
//Dina Patricia Rodríguez Pacay - 19566
//Electrónica Digital 1 - Sección 12
//Laboratorio 6 - Ejercicio 5 - Flip Flop

module FF(input clk, rst, set, input [3:0] D, output [3:0] Q);
reg Q;
	always @ (posedge clk or	posedge rst) begin
		if (rst)
		  Q <= 4'b0000;
	else
		  Q <= D;
	end
endmodule

Lab6/Ejercicio5/flipflop_tb.v
//Dina Patricia Rodríguez Pacay - 19566
//Electrónica Digital 1 - Sección 12
//Laboratorio 6 - Ejercicio 5 - Flip Flop testbench

module testbench();

  reg clk, rst, set;
  reg [3:0] A;
  wire [3:0] Y;
	FF U1(clk, A, rst, set, Y);

  initial begin
	#2
  $display("Flip Flop");
  $display("------------");
  $monitor("%b %b %b %b", Y, A, clk, set);
  rst = 0; A = 4'b0000;
  #1 rst = 1; A = 4'b0011;
  #1 A = 4'b0011;
	#1 A = 4'b1111;
	#1 A = 4'b1111;
	#1 rst = 1;
	#1 rst = 0; A = 4'b1100;
	#1 set = 1; A = 4'b1100;
	#1 set = 1; A = 4'b1111;
	#1 set = 0; A = 4'b1111;
	#1 set = 0; A = 4'b0011;
  #20 $finish;
  end

  always
   #1 clk = ~clk;

  initial begin
    $dumpfile("flipflop_tb.vcd");
    $dumpvars(0, testbench);
  end
endmodule

Lab6/Ejercicio5/flipflop_tb.vcd
$date
	Sat Sep 05 22:40:13 2020
$end
$version
	Icarus Verilog
$end
$timescale
	1ps
$end
$scope module testbench $end
$var wire 4 ! Y [3:0] $end
$var reg 4 " A [3:0] $end
$var reg 1 # clk $end
$var reg 1 $ rst $end
$var reg 1 % set $end
$scope module U1 $end
$var wire 4 & D [3:0] $end
$var wire 1 # clk $end
$var wire 1 ' rst $end
$var wire 1 $ set $end
$var reg 4 ( Q [3:0] $end
$upscope $end
$upscope $end
$enddefinitions $end
#0
$dumpvars
bx (
x'
b0x &
x%
x$
x#
bx "
bx !
$end
#2
0'
b0 "
0$
#3
b0 !
b0 (
1'
b11 "
1$
#5
b1111 "
#8
0'
b1100 "
0$
#9
b1 &
1%
#10
1'
b1111 "
#11
b0 &
0%
#12
b11 "
