Lab10/Ejercicio1/Lab10.v
//Univerrsidad Del Valle
//Electr+onica Digital
//Dina Rodríguez    19566
//Lab 10


//Ejercicio #1
module CL(input wire [11:0]d, input wire CLK, L, E, R, output reg [11:0]out);
	always @(posedge CLK or posedge L or posedge R)
		if (R) begin
			out <= 12'b0;
		end else if (L) begin
			out <= d;
		end else if (E) begin
			out <= out + 1;
		end
endmodule



//Memoria ROM
module MRom (input wire [11:0]a, output wire [7:0]d);
	reg [11:0] mem [0:4095] ;

	assign data = mem[a];

initial begin
  $readmemb("memoria.txt", mem);
end

endmodule


//Fetch
module F(input wire CLK, input wire [7:0]da, input wire E, input wire R, output [3:0]Q1, output [3:0]Q);
reg Q;
reg Q1;
wire [3:0]D1;
wire [3:0]D;
assign D[0] = da[1];
assign D[1] = da[3];
assign D[2] = da[5];
assign D[3] = da[7];
assign D1[0] = da[0];
assign D1[1] = da[2];
assign D1[2] = da[4];
assign D1[3] = da[6];

	always @(posedge CLK or posedge E or posedge R)
		if (R) begin
		Q <= 0;
		Q1 <= 0;
	end else if (E) begin
    Q <= D;
		Q1 <= D1;
	end
endmodule


module Eje1(input wire L, CLK, E1, E2, R, input wire [11:0]D, output wire [3:0]Q1, output wire [3:0]Q);
	wire [11:0]CLOUT;
	wire [7:0]MROUT;
	CL O1(D, CLK, L, E1, R, CLOUT);
	MRom O2(CLOUT, MROUT);
	F O3(CLK, MROUT, E2, R, Q1, Q);
endmodule

Lab10/Ejercicio1/Lab10_tb.v
//Univerrsidad Del Valle
//Electr+onica Digital
//Dina Rodríguez    19566

//entradas reset, clock, los 12 bits del Program Counter para hacer loads y los bits necesarios para operar los módulos Program Counter y Fetch

module Ej1();
  reg CLK, E1, E2, R, L;
  reg [11:0]D;
  wire [3:0]Q;
  wire [3:0]Q1;

	Eje1 U1(L, CLK, E1, E2, R, D, Q, Q1);

initial begin
	CLK = 0;
	forever #3 CLK = ~CLK;
end

  initial begin
	#3	$display("Ejercicio #1\n");
    $display("CLK E R L      D       |  Q1    Q0");
    $display("------------------------------------");
    $monitor("%b   %b %b %b %b %b | %b  %b", CLK, E1, E2, R, L, D, Q, Q1);
       R = 1; E1 = 0; E2 = 0; L = 0; D = 0;
    #2 R = 0;
	#15 E1 = 1; E2 = 1;
	#45 D = 50; L = 1;
	#10 L = 0;
	#10 L = 0;
  end


	initial
    #120 $finish;
  initial begin
    $dumpfile("Lab10_tb.vcd");
    $dumpvars(0, Ej1);
  end
endmodule

Lab10/Ejercicio1/Lab10_tb.vcd
$date
	Sat Nov 07 22:54:40 2020
$end
$version
	Icarus Verilog
$end
$timescale
	1ps
$end
$scope module Ej1 $end
$var wire 4 ! Q1 [3:0] $end
$var wire 4 " Q [3:0] $end
$var reg 1 # CLK $end
$var reg 12 $ D [11:0] $end
$var reg 1 % E1 $end
$var reg 1 & E2 $end
$var reg 1 ' L $end
$var reg 1 ( R $end
$scope module U1 $end
$var wire 1 # CLK $end
$var wire 12 ) D [11:0] $end
$var wire 1 % E1 $end
$var wire 1 & E2 $end
$var wire 1 ' L $end
$var wire 8 * MROUT [7:0] $end
$var wire 1 ( R $end
$var wire 4 + Q1 [3:0] $end
$var wire 4 , Q [3:0] $end
$var wire 12 - CLOUT [11:0] $end
$scope module O1 $end
$var wire 1 # CLK $end
$var wire 1 % E $end
$var wire 1 ' L $end
$var wire 1 ( R $end
$var wire 12 . d [11:0] $end
$var reg 12 / out [11:0] $end
$upscope $end
$scope module O2 $end
$var wire 12 0 a [11:0] $end
$var wire 8 1 d [7:0] $end
$var wire 1 2 data $end
$upscope $end
$scope module O3 $end
$var wire 1 # CLK $end
$var wire 1 & E $end
$var wire 1 ( R $end
$var wire 8 3 da [7:0] $end
$var wire 4 4 D1 [3:0] $end
$var wire 4 5 D [3:0] $end
$var reg 4 6 Q [3:0] $end
$var reg 4 7 Q1 [3:0] $end
$upscope $end
$upscope $end
$upscope $end
$enddefinitions $end
#0
$dumpvars
bx 7
bx 6
bz 5
bz 4
bz 3
x2
bz 1
bx 0
bx /
bx .
bx -
bx ,
bx +
bz *
bx )
x(
x'
x&
x%
bx $
0#
bx "
bx !
$end
#3
b0 -
b0 /
b0 0
b0 "
b0 +
b0 7
b0 !
b0 ,
b0 6
b0 $
b0 )
b0 .
0'
0&
0%
1(
1#
#5
0(
#6
0#
#9
1#
#12
0#
#15
1#
#18
0#
#20
bz "
bz +
bz 7
bz !
bz ,
bz 6
1&
1%
#21
b1 -
b1 /
b1 0
1#
#24
0#
#27
b10 -
b10 /
b10 0
1#
#30
0#
#33
b11 -
b11 /
b11 0
1#
#36
0#
#39
b100 -
b100 /
b100 0
1#
#42
0#
#45
b101 -
b101 /
b101 0
1#
#48
0#
#51
b110 -
b110 /
b110 0
1#
#54
0#
#57
b111 -
b111 /
b111 0
1#
#60
0#
#63
b1000 -
b1000 /
b1000 0
1#
#65
b110010 -
b110010 /
b110010 0
1'
b110010 $
b110010 )
b110010 .
#66
0#
#69
1#
#72
0#
#75
b110011 -
b110011 /
b110011 0
1#
0'
#78
0#
#81
b110100 -
b110100 /
b110100 0
1#
#84
0#
#87
b110101 -
b110101 /
b110101 0
1#
#90
0#
#93
b110110 -
b110110 /
b110110 0
1#
#96
0#
#99
b110111 -
b110111 /
b110111 0
1#
#102
0#
#105
b111000 -
b111000 /
b111000 0
1#
#108
0#
#111
b111001 -
b111001 /
b111001 0
1#
#114
0#
#117
b111010 -
b111010 /
b111010 0
1#
