Lab9/E3/E3.v
//Universidad Del Valle
//Electrónica Digital - 2020
//Dina Rodríguez

//Ejercicio 3

module FD1(input wire CLK, input wire D,  input wire E, input wire R, output Q);
reg Q;
	always @(posedge CLK or	posedge R or posedge E)
		if (R)begin
		Q <= 0;
	end else if(E) begin
		Q <= D;
	end
endmodule


module FJK(input wire CLK, E, R, J, K, output wire Q);
	FD1 O5(CLK, ~K&Q | J&~Q, R, E, Q);
endmodule

Lab9/E3/E3_tb.v
//Universidad Del Valle
//Electrónica Digital - 2020
//Dina Rodríguez

module E3();
  reg CLK, R, E, K, J;
  wire Q;

	FJK U4(CLK, R, E, J, K, Q);


initial begin
	CLK=0;
	forever #5 CLK = ~CLK;
end


  initial begin
	#3
    $display("\n");
	$display("Ejercicio #3");
    $display("CLK J K |  Q");
    $display("-----------------");
    $monitor("%b  %b %b | %b", CLK, J, K, Q);
       R = 1; E = 0; J = 0; K = 0;
    #2 R = 0;
    E = 1;
	#15 J = 1;
	#20 J = 0; K = 1;
	#25 J = 1;

  end

	initial
    #70 $finish;
  initial begin
    $dumpfile("E3_tb.vcd");
    $dumpvars(0, E3);
  end
endmodule

Lab9/E3/E3_tb.vcd
$date
	Sat Oct 31 11:56:54 2020
$end
$version
	Icarus Verilog
$end
$timescale
	1ps
$end
$scope module E3 $end
$var wire 1 ! Q $end
$var reg 1 " CLK $end
$var reg 1 # E $end
$var reg 1 $ J $end
$var reg 1 % K $end
$var reg 1 & R $end
$scope module U4 $end
$var wire 1 " CLK $end
$var wire 1 & E $end
$var wire 1 $ J $end
$var wire 1 % K $end
$var wire 1 # R $end
$var wire 1 ! Q $end
$scope module O5 $end
$var wire 1 " CLK $end
$var wire 1 ' D $end
$var wire 1 # E $end
$var wire 1 & R $end
$var reg 1 ! Q $end
$upscope $end
$upscope $end
$upscope $end
$enddefinitions $end
#0
$dumpvars
x'
x&
x%
x$
x#
0"
x!
$end
#3
0'
0!
0%
0$
0#
1&
#5
1#
0&
1"
#10
0"
#15
1"
#20
1'
0"
1$
#25
1!
1"
#30
0"
#35
1"
#40
0'
0"
1%
0$
#45
0!
1"
#50
0"
#55
1"
#60
0"
#65
1'
1"
1$
