Lab9/E1/E1.v
//Universidad Del Valle
//Electrónica Digital - 2020
//Dina Rodríguez

//Ejercicio 1


//FlipFlopDs


// (1 bit)
module FD1(input wire CLK, input wire D, input wire E, input wire R, output Q);
reg Q;
	always @(posedge CLK or	posedge R or posedge E)
		if (R)begin
		Q <= 0;
	end else if(E) begin
		Q <= D;
	end
endmodule


// (2 bits)
module FD2(input wire CLK, input wire [1:0]D, input wire E, input wire R, output wire [1:0]Q);
	FD1 O0(CLK, D[0], R, E, Q[0]);
	FD1 O1(CLK, D[1], R, E, Q[1]);
endmodule


// (4 bits)
module FD4 (input wire CLK, input wire [3:0]D, input wire E, input wire R, output wire [3:0]Q);
	FD2 O3(CLK, D[1:0], R, E, Q[1:0]);
	FD2 O4(CLK, D[3:2], R, E, Q[3:2]);
endmodule

Lab9/E1/E1_tb.v
//Universidad Del Valle
//Electrónica Digital - 2020
//Dina Rodríguez


module E1();
  reg CLK, R, D1, E;
  reg [1:0]D2;
  reg [3:0]D4;
  wire Q1;
  wire [1:0]Q2;
  wire [3:0]Q4;


	FD1 U1(CLK, D1, R, E, Q1);
	FD2 U2(CLK, D2, R, E, Q2);
	FD4 U3(CLK, D4, R, E, Q4);


initial begin
	CLK=0;
	forever #3 CLK = ~CLK;
end


  initial begin
	#3
	$display("Ejercicio #1 FlipFlops D ");
  $display("\n");

  $display("1 bit");
    $display("CLK E D | Q");
    $display("------------");
    $monitor("%b  %b %b | %b", CLK, E, D1, Q1);
       R = 1;
       D1 = 1;
       E = 0;
    #2 R = 0;
	#8 D1 = 1;
	#8 E = 1;
	#8 D1 = 0;
  end


  initial begin
	#55
    $display("\n");
	$display("2 bits");
    $display("CLK E  D | Q");
    $display("-------------");
    $monitor("%b   %b %b |%b", CLK, E, D2, Q2);
      R = 1;
      D1 = 1;
      E = 0;
    #2 R = 0;
 #8 D1 = 1;
  #8 E = 1;
  #8 D1 = 0;
  end


  initial begin
	#98
    $display("\n");
	$display("Ejercicio 1, FlipFlop D 4 bits");
    $display("Clk E  D   |  Q");
    $display("-----------------");
    $monitor("%b   %b %b | %b", CLK, E, D4, Q4);
      R = 1;
      D1 = 1;
      E = 0;
    #2 R = 0;
 #8 D1 = 1;
  #8 E = 1;
  #8 D1 = 0;
  end


	initial
    #135 $finish;
  initial begin
    $dumpfile("E1_tb.vcd");
    $dumpvars(0, E1);
  end
endmodule

Lab9/E1/E1_tb.vcd
$date
	Sat Oct 31 11:43:57 2020
$end
$version
	Icarus Verilog
$end
$timescale
	1ps
$end
$scope module E1 $end
$var wire 4 ! Q4 [3:0] $end
$var wire 2 " Q2 [1:0] $end
$var wire 1 # Q1 $end
$var reg 1 $ CLK $end
$var reg 1 % D1 $end
$var reg 2 & D2 [1:0] $end
$var reg 4 ' D4 [3:0] $end
$var reg 1 ( E $end
$var reg 1 ) R $end
$scope module U1 $end
$var wire 1 $ CLK $end
$var wire 1 % D $end
$var wire 1 ) E $end
$var wire 1 ( R $end
$var reg 1 # Q $end
$upscope $end
$scope module U2 $end
$var wire 1 $ CLK $end
$var wire 2 * D [1:0] $end
$var wire 1 ) E $end
$var wire 1 ( R $end
$var wire 2 + Q [1:0] $end
$scope module O0 $end
$var wire 1 $ CLK $end
$var wire 1 , D $end
$var wire 1 ( E $end
$var wire 1 ) R $end
$var reg 1 - Q $end
$upscope $end
$scope module O1 $end
$var wire 1 $ CLK $end
$var wire 1 . D $end
$var wire 1 ( E $end
$var wire 1 ) R $end
$var reg 1 / Q $end
$upscope $end
$upscope $end
$scope module U3 $end
$var wire 1 $ CLK $end
$var wire 4 0 D [3:0] $end
$var wire 1 ) E $end
$var wire 1 ( R $end
$var wire 4 1 Q [3:0] $end
$scope module O3 $end
$var wire 1 $ CLK $end
$var wire 2 2 D [1:0] $end
$var wire 1 ( E $end
$var wire 1 ) R $end
$var wire 2 3 Q [1:0] $end
$scope module O0 $end
$var wire 1 $ CLK $end
$var wire 1 4 D $end
$var wire 1 ) E $end
$var wire 1 ( R $end
$var reg 1 5 Q $end
$upscope $end
$scope module O1 $end
$var wire 1 $ CLK $end
$var wire 1 6 D $end
$var wire 1 ) E $end
$var wire 1 ( R $end
$var reg 1 7 Q $end
$upscope $end
$upscope $end
$scope module O4 $end
$var wire 1 $ CLK $end
$var wire 2 8 D [1:0] $end
$var wire 1 ( E $end
$var wire 1 ) R $end
$var wire 2 9 Q [1:0] $end
$scope module O0 $end
$var wire 1 $ CLK $end
$var wire 1 : D $end
$var wire 1 ) E $end
$var wire 1 ( R $end
$var reg 1 ; Q $end
$upscope $end
$scope module O1 $end
$var wire 1 $ CLK $end
$var wire 1 < D $end
$var wire 1 ) E $end
$var wire 1 ( R $end
$var reg 1 = Q $end
$upscope $end
$upscope $end
$upscope $end
$upscope $end
$enddefinitions $end
#0
$dumpvars
x=
x<
x;
x:
bx 9
bx 8
x7
x6
x5
x4
bx 3
bx 2
bx 1
bx 0
x/
x.
x-
x,
bx +
bx *
x)
x(
bx '
bx &
x%
0$
x#
bx "
bx !
$end
#3
1#
0-
b0 "
b0 +
0/
0(
1%
1)
1$
#5
0)
#6
0$
#9
1$
#12
0$
#15
1$
#18
0$
#21
0=
b0 9
0;
07
b0 !
b0 1
b0 3
05
x/
bx "
bx +
x-
0#
1$
1(
#24
0$
#27
1$
#29
0%
#30
0$
#33
1$
#36
0$
#39
1$
#42
0$
#45
1$
#48
0$
#51
1$
#54
0$
#55
x=
bx 9
x;
x7
bx !
bx 1
bx 3
x5
0/
b0 "
b0 +
0-
1#
0(
1%
1)
#57
0)
1$
#60
0$
#63
1$
#66
0$
#69
1$
#72
0$
#73
0=
b0 9
0;
07
b0 !
b0 1
b0 3
05
x/
bx "
bx +
x-
0#
1(
#75
1$
#78
0$
#81
1$
0%
#84
0$
#87
1$
#90
0$
#93
1$
#96
0$
#98
1#
0-
b0 "
b0 +
0/
x5
bx 3
x7
x;
bx !
bx 1
bx 9
x=
0(
1%
1)
#99
1$
#100
0)
#102
0$
#105
1$
#108
0$
#111
1$
#114
0$
#116
0#
x-
bx "
bx +
x/
05
b0 3
07
0;
b0 !
b0 1
b0 9
0=
1(
#117
1$
#120
0$
#123
1$
#124
0%
