Lab4/ejercicio.v



// Gate Level Modeling

module gateLeveling1(input wire A, B, C, output wire Y);  // ejercicio1.1

  wire a1,b1,c1,o1,o2,o3;

  not (a1, A);
  not (b1, B);
  not (c1, C);
  and (o1, a1, c1);
  and (o2, A, b1);
  and (o3, A, c1);
  or  (Y, o1, o2, o3);

endmodule  // ejercicio1.1


module gateLeveling2(input wire A, B, C, output wire Y);  // ejercicio1.2

  not (Y, B);

endmodule  // ejercicio1.2

//end Gate Level Modeling

module gateLeveling3(input wire A, B, C, D, output wire Y);  // ejercicio1.3

  wire a1,b1,c1,d1,o1,o2,o3,o4,o5,o6,o7,o8;

  not (a1, A);
  not (b1, B);
  not (c1, C);
  not (d1, D);
  and (o1, a1, b1, c1, d1);
  and (o2, A, B, c1, d1);
  and (o3, a1, B, c1, D);
  and (o4, A, b1, c1, D);
  and (o5, a1, b1, C, D);
  and (o6, A, B, C, D);
  and (o7, a1, B, C, d1);
  and (o8, A, b1, C, d1);
  or  (Y, o1, o2, o3, o4, o5, o6, o7, o8);

endmodule  // ejercicio1.3

module gateLeveling4(input wire A, B, C, D, output wire Y);  // ejercicio1.4

  wire d1,o1,o2,o3,o4,o5,o6,o7,o8;

  not (d1, D);
  and (o1, A, d1);
  and (o2, A, C);
  and (o3, A, B);
  or  (Y, o1, o2, o3);

endmodule  // ejercicio1.4

//operadores lógicos

module gates1(input wire a, b, c, d, output wire y1); //ejercicio2.1

  assign y1 = ~b & ~c & ~d |
              a & ~c |
              a & ~d |
              a & ~b ;

endmodule //end ejercicio2.1


module gates2(input wire a, b, c, output wire y1); //ejercicio2.2

  assign y1 = c |
              a |
               ~b ;

endmodule //end ejercicio2.2


module gates3(input wire a, b, c, d, output wire y1); //ejercicio2.3

  assign y1 = ~c & d |
              a & d  |
               ~b ;

endmodule //end ejercicio2.3

module gates4(input wire a, b, c, output wire y1); //ejercicio2.4

  assign y1 = ~c & ~a |
              b ;

endmodule //end ejercicio2.4
//operadores lógicos end

Lab4/ejercicio_tb.v


module testbench();

reg A1,A2,A3,A4,A5,A6,A7,A8,B1,B2,B3,B4,B5,B6,B7,B8,C1,C2,C3,C4,C5,C6,C7,C8,D1,D2,D3,D4,D5,D6,D7,D8;
wire Y1,Y2,Y3,Y4,Y5,Y6,Y7,Y8;

gateLeveling1 U1(A1, B1, C1, Y1);  //ejercicio1.1
gateLeveling2 U2(A2, B2, C2, Y2); //ejercicio1.2
gateLeveling3 U3(A3, B3, C3, D3, Y3);  //ejercicio1.3
gateLeveling4 U4(A4, B4, C4, D4, Y4);   //ejercicio1.4

gates1 U5(A5, B5, C5, D5, Y5);   //ejercicio2.1
gates2 U6(A6, B6, C6, Y6);   //ejercicio2.2
gates3 U7(A7, B7, C7, D7, Y7);   //ejercicio2.3
gates4 U8(A8, B8, C8, Y8);   //ejercicio2.4

initial begin
  $display("-------------");
  $display("| A B C | Y |");
  $display("|-------|---|");
  $monitor("| %b %b %b | %b |",
  A1,B1,C1,Y1);
  A1=0;
  B1=0;
  C1=0;
  #1 C1=1;
  #1 B1=1; C1=0;
  #1 C1=1;
  #1 A1=1; B1=0; C1=0;
  #1 C1=1;
  #1 B1=1; C1=0;
  #1 C1=1;
  #1 $display("-------------");
  #1 $finish;
end

initial begin
  $display("-------------");
  $display("| A B C | Y |");
  $display("|-------|---|");
  $monitor("| %b %b %b | %b |",
  A2,B2,C2,Y2);
  A2=0;
  B2=0;
  C2=0;
  #1 C2=1;
  #1 B2=1; C2=0;
  #1 C2=1;
  #1 A2=1; B2=0; C2=0;
  #1 C2=1;
  #1 B2=1; C2=0;
  #1 C2=1;
  #1 $display("-------------");
  #1 $finish;
end

initial begin
  $display("---------------");
  $display("| A B C D | Y |");
  $display("|---------|---|");
  $monitor("| %b %b %b %b | %b |",
  A3,B3,C3,D3,Y3);
  A3=0;
  B3=0;
  C3=0;
  D3=0;
  #1 D3=1;
  #1 C3=1; D3=0;
  #1 D3=1;
  #1 B3=1; C3=0; D3=0;
  #1 D3=1;
  #1 C3=1; D3=0;
  #1 D3=1;
  #1 A3=1; B3=0; C3=0; D3=0;
  #1 D3=1;
  #1 C3=1; D3=0;
  #1 D3=1;
  #1 B3=1; C3=0; D3=0;
  #1 D3=1;
  #1 C3=1; D3=0;
  #1 D3=1;
  #1 $display("---------------");
  #1 $finish;
end


initial begin
  $display("---------------");
  $display("| A B C D | Y |");
  $display("|---------|---|");
  $monitor("| %b %b %b %b | %b |",
  A4,B4,C4,D4,Y4);
  A4=0;
  B4=0;
  C4=0;
  D4=0;
  #1 D4=1;
  #1 C4=1; D4=0;
  #1 D4=1;
  #1 B4=1; C4=0; D4=0;
  #1 D4=1;
  #1 C4=1; D4=0;
  #1 D4=1;
  #1 A4=1; B4=0; C4=0; D4=0;
  #1 D4=1;
  #1 C4=1; D4=0;
  #1 D4=1;
  #1 B4=1; C4=0; D4=0;
  #1 D4=1;
  #1 C4=1; D4=0;
  #1 D4=1;
  #1 $display("---------------");
  #1 $finish;
end


initial begin
  $display("---------------");
  $display("| A B C D | Y |");
  $display("|---------|---|");
  $monitor("| %b %b %b %b | %b |",
  A5,B5,C5,D5,Y5);
  A5=0;
  B5=0;
  C5=0;
  D5=0;
  #1 D5=1;
  #1 C5=1; D5=0;
  #1 D5=1;
  #1 B5=1; C5=0; D5=0;
  #1 D5=1;
  #1 C5=1; D5=0;
  #1 D5=1;
  #1 A5=1; B5=0; C5=0; D5=0;
  #1 D5=1;
  #1 C5=1; D5=0;
  #1 D5=1;
  #1 B5=1; C5=0; D5=0;
  #1 D5=1;
  #1 C5=1; D5=0;
  #1 D5=1;
  #1 $display("---------------");
  #1 $finish;
end



initial begin
  $display("-------------");
  $display("| A B C | Y |");
  $display("|-------|---|");
  $monitor("| %b %b %b | %b |",
  A6,B6,C6,Y6);
  A6=0;
  B6=0;
  C6=0;
  #1 C6=1;
  #1 B6=1; C6=0;
  #1 C6=1;
  #1 A6=1; B6=0; C6=0;
  #1 C6=1;
  #1 B6=1; C6=0;
  #1 C6=1;
  #1 $display("-------------");
  #1 $finish;
end


initial begin
  $display("---------------");
  $display("| A B C D | Y |");
  $display("|---------|---|");
  $monitor("| %b %b %b %b | %b |",
  A7,B7,C7,D7,Y7);
  A7=0;
  B7=0;
  C7=0;
  D7=0;
  #1 D7=1;
  #1 C7=1; D7=0;
  #1 D7=1;
  #1 B7=1; C7=0; D7=0;
  #1 D7=1;
  #1 C7=1; D7=0;
  #1 D7=1;
  #1 A7=1; B7=0; C7=0; D7=0;
  #1 D7=1;
  #1 C7=1; D7=0;
  #1 D7=1;
  #1 B7=1; C7=0; D7=0;
  #1 D7=1;
  #1 C7=1; D7=0;
  #1 D7=1;
  #1 $display("---------------");
  #1 $finish;
end



initial begin
  $display("-------------");
  $display("| A B C | Y |");
  $display("|-------|---|");
  $monitor("| %b %b %b | %b |",
  A8,B8,C8,Y8);
  A8=0;
  B8=0;
  C8=0;
  #1 C8=1;
  #1 B8=1; C8=0;
  #1 C8=1;
  #1 A8=1; B8=0; C8=0;
  #1 C8=1;
  #1 B8=1; C8=0;
  #1 C8=1;
  #1 $display("-------------");
  #1 $finish;
end

  initial
    #60 $finish;

  initial
    begin
      $dumpfile("ejercicio_tb.vcd");
      $dumpvars(0,testbench);
    end
endmodule

Lab4/ejercicio_tb.vcd
$date
	Sun Aug 09 23:38:47 2020
$end
$version
	Icarus Verilog
$end
$timescale
	1ps
$end
$scope module testbench $end
$var wire 1 ! Y8 $end
$var wire 1 " Y7 $end
$var wire 1 # Y6 $end
$var wire 1 $ Y5 $end
$var wire 1 % Y4 $end
$var wire 1 & Y3 $end
$var wire 1 ' Y2 $end
$var wire 1 ( Y1 $end
$var reg 1 ) A1 $end
$var reg 1 * A2 $end
$var reg 1 + A3 $end
$var reg 1 , A4 $end
$var reg 1 - A5 $end
$var reg 1 . A6 $end
$var reg 1 / A7 $end
$var reg 1 0 A8 $end
$var reg 1 1 B1 $end
$var reg 1 2 B2 $end
$var reg 1 3 B3 $end
$var reg 1 4 B4 $end
$var reg 1 5 B5 $end
$var reg 1 6 B6 $end
$var reg 1 7 B7 $end
$var reg 1 8 B8 $end
$var reg 1 9 C1 $end
$var reg 1 : C2 $end
$var reg 1 ; C3 $end
$var reg 1 < C4 $end
$var reg 1 = C5 $end
$var reg 1 > C6 $end
$var reg 1 ? C7 $end
$var reg 1 @ C8 $end
$var reg 1 A D3 $end
$var reg 1 B D4 $end
$var reg 1 C D5 $end
$var reg 1 D D7 $end
$scope module U1 $end
$var wire 1 ) A $end
$var wire 1 1 B $end
$var wire 1 9 C $end
$var wire 1 ( Y $end
$var wire 1 E a1 $end
$var wire 1 F b1 $end
$var wire 1 G c1 $end
$var wire 1 H o1 $end
$var wire 1 I o2 $end
$var wire 1 J o3 $end
$upscope $end
$scope module U2 $end
$var wire 1 * A $end
$var wire 1 2 B $end
$var wire 1 : C $end
$var wire 1 ' Y $end
$upscope $end
$scope module U3 $end
$var wire 1 + A $end
$var wire 1 3 B $end
$var wire 1 ; C $end
$var wire 1 A D $end
$var wire 1 & Y $end
$var wire 1 K a1 $end
$var wire 1 L b1 $end
$var wire 1 M c1 $end
$var wire 1 N d1 $end
$var wire 1 O o1 $end
$var wire 1 P o2 $end
$var wire 1 Q o3 $end
$var wire 1 R o4 $end
$var wire 1 S o5 $end
$var wire 1 T o6 $end
$var wire 1 U o7 $end
$var wire 1 V o8 $end
$upscope $end
$scope module U4 $end
$var wire 1 , A $end
$var wire 1 4 B $end
$var wire 1 < C $end
$var wire 1 B D $end
$var wire 1 % Y $end
$var wire 1 W d1 $end
$var wire 1 X o1 $end
$var wire 1 Y o2 $end
$var wire 1 Z o3 $end
$upscope $end
$scope module U5 $end
$var wire 1 - a $end
$var wire 1 5 b $end
$var wire 1 = c $end
$var wire 1 C d $end
$var wire 1 $ y1 $end
$upscope $end
$scope module U6 $end
$var wire 1 . a $end
$var wire 1 6 b $end
$var wire 1 > c $end
$var wire 1 # y1 $end
$upscope $end
$scope module U7 $end
$var wire 1 / a $end
$var wire 1 7 b $end
$var wire 1 ? c $end
$var wire 1 D d $end
$var wire 1 " y1 $end
$upscope $end
$scope module U8 $end
$var wire 1 0 a $end
$var wire 1 8 b $end
$var wire 1 @ c $end
$var wire 1 ! y1 $end
$upscope $end
$upscope $end
$enddefinitions $end
#0
$dumpvars
0Z
0Y
0X
1W
0V
0U
0T
0S
0R
0Q
0P
1O
1N
1M
1L
1K
0J
0I
1H
1G
1F
1E
0D
0C
0B
0A
0@
0?
0>
0=
0<
0;
0:
09
08
07
06
05
04
03
02
01
00
0/
0.
0-
0,
0+
0*
0)
1(
1'
1&
0%
1$
1#
1"
1!
$end
#1
0$
0&
0!
0(
0O
0H
0W
0N
0G
1@
1D
1>
1C
1B
1A
1:
19
#2
1(
0#
1H
1!
1W
1N
0M
0'
1G
0F
0@
18
0D
1?
0>
16
0C
1=
0B
1<
0A
1;
0:
12
09
11
#3
1&
0(
1#
0H
0W
0N
1S
0G
1@
1D
1>
1C
1B
1A
1:
19
#4
0&
1(
0"
1J
1I
0!
1W
1N
1M
0S
0L
1'
1G
1F
0E
0@
08
10
0D
0?
17
0>
06
1.
0C
0=
15
0B
0<
14
0A
0;
13
0:
02
1*
09
01
1)
#5
1"
1&
0J
0W
0N
1Q
0G
1@
1D
1>
1C
1B
1A
1:
19
#6
0"
1&
1U
1J
0I
1!
1W
1N
0Q
0M
0'
1G
0F
0@
18
0D
1?
0>
16
0C
1=
0B
1<
0A
1;
0:
12
09
11
#7
0&
0(
0U
0J
0W
0N
0G
1@
1D
1>
1C
1B
1A
1:
19
#8
1$
1%
1"
1X
1W
1N
1M
1L
0K
0D
0?
07
1/
0C
0=
05
1-
0B
0<
04
1,
0A
0;
03
1+
#9
0%
1&
0X
0W
0N
1R
1D
1C
1B
1A
