Lab5/ejercicio4.v



//MUX 2:1
module mux21(input V0, V1, A, output wire Y);

	assign Y = V0 ? V1 : V0; // Asigna a Y con una condición (?)

endmodule

//MUX 4:1
module mux41(input V0, V1, V2, V3, A, B, output wire Y);

	wire [1:0] Y1;
	mux21 U1(V0, V1, B, Y1[0]);
	mux21 U2(V2, V3, B, Y1[1]);
	mux21 U3(Y1[0], Y1[1] , A, Y);

endmodule


// MUX 8:1
module mux81(input V0, V1, V2, V3, V4, V5, V6, V7, A, B, C, output wire Y);

	wire [1:0] Y1;
	mux41 U4(V0, V1, V2, V3, C, B, Y1[0]);
	mux41 U5(V4, V5, V6, V7, C, B, Y1[1]);
	mux21 U6(Y1[0], Y1[1], A, Y);

endmodule


//MUX 2:1 – tabla1
module t1mux21(input wire A, B, C, output wire Y);

	mux21 U7(B^C, B~^C, A, Y);

endmodule


//MUX 4:1 – tabla1
module t1mux41(input wire A, B, C, output wire Y);

	mux41 U8(C, ~C, ~C, C, A, B, Y);

endmodule


//MUX 8:1 – tabla1
module t1mux81(input wire A, B, C, output wire Y);

	wire V, T; // VOLTAJE Y TIERRA
	assign V = 1;
	assign T = 0;
	mux81 U9(T, V, V, T, V, T, T, V, A, B, C, Y); //SEGÚN LA TABLA

endmodule


//MUX 2:1 - tabla2
module t2mux21(input wire A, B, C, output wire Y);

	mux21 U10(~(B|C), ~(B&C), A, Y);

endmodule


//MUX 4:1 – tabla2
module t2mux41(input wire A, B, C, output wire Y);

  wire V, T; // VOLTAJE Y TIERRA
  assign V = 1;
  assign T = 0;
	mux41 U11(V, T, V, ~C, A, B, Y);

endmodule


//MUX 8:1 – tabla2
module t2mux81(input wire A, B, C, output wire Y);

	wire V, T;  // VOLTAJE Y TIERRA
	assign V = 1;
	assign T = 0;
	mux81 U12(V, T, T, T, V, V, V, T, A, B, C, Y);

endmodule

Lab5/ejercicio4_tb.v


module testbench();


  reg a21, b21, c21, a41, b41, c41, a81, b81, c81, a221, b221, c221, a241, b241, c241, a281, b281, c281;
  wire t1mux21, t1mux41, t1mux81, t2mux21, t2mux41, t2mux81;

//GLM
	t1mux21 U13(a21, b21, c21, t1mux21);
	t1mux41 U14(a41, b41, c41, t1mux41);
	t1mux81 U15(a81, b81, c81, t1mux81);
	t2mux21 U16(a221, b221, c221, t2mux21);
	t2mux41 U17(a241, b241, c241, t2mux41);
	t2mux81 U18(a281, b281, c281, t2mux81);

//MUX 2:1 - tabla1
  initial begin
	#2
	$display("Tabla 1 - MUX 2:1");
  $display("-------------");
  $display("| A B C | Y |");
  $display("|-------|---|");
  $monitor("| %b %b %b | %b |", a21, b21, c21, t1mux21);
  a21=0;
  b21=0;
  c21=0;
  #1 c21=1;
  #1 b21=1; c21=0;
  #1 c21=1;
  #1 a21=1; b21=0; c21=0;
  #1 c21=1;
  #1 b21=1; c21=0;
  #1 c21=1;
  #1 $display("-------------");
  end


  //MUX 4:1 - tabla1
  initial begin
  #12
  $display("Tabla 1 - MUX 4:1");
  $display("-------------");
  $display("| A B C | Y |");
  $display("|-------|---|");
  $monitor("| %b %b %b | %b |", a41, b41, c41, t1mux41);
  a41=0;
  b41=0;
  c41=0;
  #1 c41=1;
  #1 b41=1; c41=0;
  #1 c41=1;
  #1 a41=1; b41=0; c41=0;
  #1 c41=1;
  #1 b41=1; c41=0;
  #1 c41=1;
  #1 $display("-------------");
  end


  //MUX 8:1 - tabla1
  initial begin
  #22
  $display("Tabla 1 - MUX 8:1");
  $display("-------------");
  $display("| A B C | Y |");
  $display("|-------|---|");
  $monitor("| %b %b %b | %b |", a81, b81, c81, t1mux81);
  a81=0;
  b81=0;
  c81=0;
  #1 c81=1;
  #1 b81=1; c81=0;
  #1 c81=1;
  #1 a81=1; b81=0; c81=0;
  #1 c81=1;
  #1 b81=1; c81=0;
  #1 c81=1;
  #1 $display("-------------");
  end

  //MUX 2:1 – tabla2
  initial begin
	#32
	$display("Tabla 2 - MUX 2:1");
  $display("-------------");
  $display("| A B C | Y |");
  $display("|-------|---|");
  $monitor("| %b %b %b | %b |", a221, b221, c221, t2mux21);
  a221=0;
  b221=0;
  c221=0;
  #1 c221=1;
  #1 b221=1; c221=0;
  #1 c221=1;
  #1 a221=1; b221=0; c221=0;
  #1 c221=1;
  #1 b221=1; c221=0;
  #1 c221=1;
  #1 $display("-------------");
  end


  //MUX 4:1 – tabla2
  initial begin
  #42
  $display("Tabla 2 - MUX 4:1");
  $display("-------------");
  $display("| A B C | Y |");
  $display("|-------|---|");
  $monitor("| %b %b %b | %b |", a241, b241, c241, t2mux41);
  a241=0;
  b241=0;
  c241=0;
  #1 c241=1;
  #1 b241=1; c241=0;
  #1 c241=1;
  #1 a241=1; b241=0; c241=0;
  #1 c241=1;
  #1 b241=1; c241=0;
  #1 c241=1;
  #1 $display("-------------");
  end


  //MUX 8:1 – tabla2
  initial begin
  #52
  $display("Tabla 2 - MUX 8:1");
  $display("-------------");
  $display("| A B C | Y |");
  $display("|-------|---|");
  $monitor("| %b %b %b | %b |", a281, b281, c281, t2mux81);
  a281=0;
  b281=0;
  c281=0;
  #1 c281=1;
  #1 b281=1; c281=0;
  #1 c281=1;
  #1 a281=1; b281=0; c281=0;
  #1 c281=1;
  #1 b281=1; c281=0;
  #1 c281=1;
  #1 $display("-------------");
  end


  initial
    #62 $finish;

  initial begin
    $dumpfile("ejercicio4_tb.vcd");
    $dumpvars(0, testbench);
  end


endmodule

Lab5/ejercicio4_tb.vcd
$date
	Sun Aug 16 01:45:01 2020
$end
$version
	Icarus Verilog
$end
$timescale
	1ps
$end
$scope module testbench $end
$var wire 1 ! t2mux81 $end
$var wire 1 " t2mux41 $end
$var wire 1 # t2mux21 $end
$var wire 1 $ t1mux81 $end
$var wire 1 % t1mux41 $end
$var wire 1 & t1mux21 $end
$var reg 1 ' a21 $end
$var reg 1 ( a221 $end
$var reg 1 ) a241 $end
$var reg 1 * a281 $end
$var reg 1 + a41 $end
$var reg 1 , a81 $end
$var reg 1 - b21 $end
$var reg 1 . b221 $end
$var reg 1 / b241 $end
$var reg 1 0 b281 $end
$var reg 1 1 b41 $end
$var reg 1 2 b81 $end
$var reg 1 3 c21 $end
$var reg 1 4 c221 $end
$var reg 1 5 c241 $end
$var reg 1 6 c281 $end
$var reg 1 7 c41 $end
$var reg 1 8 c81 $end
$scope module U13 $end
$var wire 1 ' A $end
$var wire 1 - B $end
$var wire 1 3 C $end
$var wire 1 & Y $end
$scope module U7 $end
$var wire 1 ' A $end
$var wire 1 9 V0 $end
$var wire 1 : V1 $end
$var wire 1 & Y $end
$upscope $end
$upscope $end
$scope module U14 $end
$var wire 1 + A $end
$var wire 1 1 B $end
$var wire 1 7 C $end
$var wire 1 % Y $end
$scope module U8 $end
$var wire 1 + A $end
$var wire 1 1 B $end
$var wire 1 7 V0 $end
$var wire 1 ; V1 $end
$var wire 1 < V2 $end
$var wire 1 7 V3 $end
$var wire 2 = Y1 [1:0] $end
$var wire 1 % Y $end
$scope module U1 $end
$var wire 1 1 A $end
$var wire 1 7 V0 $end
$var wire 1 ; V1 $end
$var wire 1 > Y $end
$upscope $end
$scope module U2 $end
$var wire 1 1 A $end
$var wire 1 < V0 $end
$var wire 1 7 V1 $end
$var wire 1 ? Y $end
$upscope $end
$scope module U3 $end
$var wire 1 + A $end
$var wire 1 @ V0 $end
$var wire 1 A V1 $end
$var wire 1 % Y $end
$upscope $end
$upscope $end
$upscope $end
$scope module U15 $end
$var wire 1 , A $end
$var wire 1 2 B $end
$var wire 1 8 C $end
$var wire 1 B T $end
$var wire 1 C V $end
$var wire 1 $ Y $end
$scope module U9 $end
$var wire 1 , A $end
$var wire 1 2 B $end
$var wire 1 8 C $end
$var wire 1 B V0 $end
$var wire 1 C V1 $end
$var wire 1 C V2 $end
$var wire 1 B V3 $end
$var wire 1 C V4 $end
$var wire 1 B V5 $end
$var wire 1 B V6 $end
$var wire 1 C V7 $end
$var wire 2 D Y1 [1:0] $end
$var wire 1 $ Y $end
$scope module U4 $end
$var wire 1 8 A $end
$var wire 1 2 B $end
$var wire 1 B V0 $end
$var wire 1 C V1 $end
$var wire 1 C V2 $end
$var wire 1 B V3 $end
$var wire 2 E Y1 [1:0] $end
$var wire 1 F Y $end
$scope module U1 $end
$var wire 1 2 A $end
$var wire 1 B V0 $end
$var wire 1 C V1 $end
$var wire 1 G Y $end
$upscope $end
$scope module U2 $end
$var wire 1 2 A $end
$var wire 1 C V0 $end
$var wire 1 B V1 $end
$var wire 1 H Y $end
$upscope $end
$scope module U3 $end
$var wire 1 8 A $end
$var wire 1 I V0 $end
$var wire 1 J V1 $end
$var wire 1 F Y $end
$upscope $end
$upscope $end
$scope module U5 $end
$var wire 1 8 A $end
$var wire 1 2 B $end
$var wire 1 C V0 $end
$var wire 1 B V1 $end
$var wire 1 B V2 $end
$var wire 1 C V3 $end
$var wire 2 K Y1 [1:0] $end
$var wire 1 L Y $end
$scope module U1 $end
$var wire 1 2 A $end
$var wire 1 C V0 $end
$var wire 1 B V1 $end
$var wire 1 M Y $end
$upscope $end
$scope module U2 $end
$var wire 1 2 A $end
$var wire 1 B V0 $end
$var wire 1 C V1 $end
$var wire 1 N Y $end
$upscope $end
$scope module U3 $end
$var wire 1 8 A $end
$var wire 1 O V0 $end
$var wire 1 P V1 $end
$var wire 1 L Y $end
$upscope $end
$upscope $end
$scope module U6 $end
$var wire 1 , A $end
$var wire 1 Q V0 $end
$var wire 1 R V1 $end
$var wire 1 $ Y $end
$upscope $end
$upscope $end
$upscope $end
$scope module U16 $end
$var wire 1 ( A $end
$var wire 1 . B $end
$var wire 1 4 C $end
$var wire 1 # Y $end
$scope module U10 $end
$var wire 1 ( A $end
$var wire 1 S V0 $end
$var wire 1 T V1 $end
$var wire 1 # Y $end
$upscope $end
$upscope $end
$scope module U17 $end
$var wire 1 ) A $end
$var wire 1 / B $end
$var wire 1 5 C $end
$var wire 1 U T $end
$var wire 1 V V $end
$var wire 1 " Y $end
$scope module U11 $end
$var wire 1 ) A $end
$var wire 1 / B $end
$var wire 1 V V0 $end
$var wire 1 U V1 $end
$var wire 1 V V2 $end
$var wire 1 W V3 $end
$var wire 2 X Y1 [1:0] $end
$var wire 1 " Y $end
$scope module U1 $end
$var wire 1 / A $end
$var wire 1 V V0 $end
$var wire 1 U V1 $end
$var wire 1 Y Y $end
$upscope $end
$scope module U2 $end
$var wire 1 / A $end
$var wire 1 V V0 $end
$var wire 1 W V1 $end
$var wire 1 Z Y $end
$upscope $end
$scope module U3 $end
$var wire 1 ) A $end
$var wire 1 [ V0 $end
$var wire 1 \ V1 $end
$var wire 1 " Y $end
$upscope $end
$upscope $end
$upscope $end
$scope module U18 $end
$var wire 1 * A $end
$var wire 1 0 B $end
$var wire 1 6 C $end
$var wire 1 ] T $end
$var wire 1 ^ V $end
$var wire 1 ! Y $end
$scope module U12 $end
$var wire 1 * A $end
$var wire 1 0 B $end
$var wire 1 6 C $end
$var wire 1 ^ V0 $end
$var wire 1 ] V1 $end
$var wire 1 ] V2 $end
$var wire 1 ] V3 $end
$var wire 1 ^ V4 $end
$var wire 1 ^ V5 $end
$var wire 1 ^ V6 $end
$var wire 1 ] V7 $end
$var wire 2 _ Y1 [1:0] $end
$var wire 1 ! Y $end
$scope module U4 $end
$var wire 1 6 A $end
$var wire 1 0 B $end
$var wire 1 ^ V0 $end
$var wire 1 ] V1 $end
$var wire 1 ] V2 $end
$var wire 1 ] V3 $end
$var wire 2 ` Y1 [1:0] $end
$var wire 1 a Y $end
$scope module U1 $end
$var wire 1 0 A $end
$var wire 1 ^ V0 $end
$var wire 1 ] V1 $end
$var wire 1 b Y $end
$upscope $end
$scope module U2 $end
$var wire 1 0 A $end
$var wire 1 ] V0 $end
$var wire 1 ] V1 $end
$var wire 1 c Y $end
$upscope $end
$scope module U3 $end
$var wire 1 6 A $end
$var wire 1 d V0 $end
$var wire 1 e V1 $end
$var wire 1 a Y $end
$upscope $end
$upscope $end
$scope module U5 $end
$var wire 1 6 A $end
$var wire 1 0 B $end
$var wire 1 ^ V0 $end
$var wire 1 ^ V1 $end
$var wire 1 ^ V2 $end
$var wire 1 ] V3 $end
$var wire 2 f Y1 [1:0] $end
$var wire 1 g Y $end
$scope module U1 $end
$var wire 1 0 A $end
$var wire 1 ^ V0 $end
$var wire 1 ^ V1 $end
$var wire 1 h Y $end
$upscope $end
$scope module U2 $end
$var wire 1 0 A $end
$var wire 1 ^ V0 $end
$var wire 1 ] V1 $end
$var wire 1 i Y $end
$upscope $end
$scope module U3 $end
$var wire 1 6 A $end
$var wire 1 j V0 $end
$var wire 1 k V1 $end
$var wire 1 g Y $end
$upscope $end
$upscope $end
$scope module U6 $end
$var wire 1 * A $end
$var wire 1 l V0 $end
$var wire 1 m V1 $end
$var wire 1 ! Y $end
$upscope $end
$upscope $end
$upscope $end
$upscope $end
$enddefinitions $end
#0
$dumpvars
0m
0l
0k
1j
0i
1h
0g
b1 f
0e
0d
0c
0b
0a
b0 `
b0 _
1^
0]
x\
0[
xZ
0Y
bx0 X
xW
1V
0U
xT
xS
0R
0Q
0P
0O
0N
0M
0L
b0 K
0J
0I
0H
0G
0F
b0 E
b0 D
1C
0B
xA
x@
x?
x>
bx =
x<
x;
x:
x9
x8
x7
x6
x5
x4
x3
x2
x1
x0
x/
x.
x-
x,
x+
x*
x)
x(
x'
x&
x%
0$
x#
0"
0!
$end
#2
0&
09
1:
03
0-
0'
#3
19
0:
13
#4
03
1-
#5
09
1:
13
#6
03
0-
1'
#7
19
0:
13
#8
03
1-
#9
09
1:
13
#12
0A
0%
0?
0@
1;
1<
b0 =
0>
07
01
0+
#13
0%
0@
0A
0;
0<
0>
b0 =
0?
17
#14
1;
1<
07
11
#15
0%
0@
0A
0;
0<
0>
b0 =
0?
17
#16
1;
1<
07
01
1+
#17
0%
0@
0A
0;
0<
0>
b0 =
0?
17
#18
1;
1<
07
11
#19
0%
0@
0A
0;
0<
0>
b0 =
0?
17
#22
08
02
0,
#23
18
#24
08
12
#25
18
#26
08
02
1,
#27
18
#28
08
12
#29
18
#32
1#
1S
1T
04
0.
0(
#33
0#
0S
14
#34
04
1.
#35
0T
14
#36
1#
1S
1T
04
0.
1(
#37
0#
0S
14
#38
04
1.
#39
0T
14
#42
1\
b10 X
1Z
1W
05
0/
0)
#43
0\
b0 X
0Z
0W
15
#44
1\
b10 X
1Z
1W
05
1/
#45
0\
b0 X
0Z
0W
15
#46
1\
b10 X
1Z
1W
05
0/
1)
#47
0\
b0 X
0Z
0W
15
#48
1\
b10 X
1Z
1W
05
1/
#49
0\
b0 X
0Z
0W
15
#52
06
00
0*
#53
16
#54
06
10
#55
16
#56
06
00
1*
#57
16
#58
06
10
#59
16
